probablyprofit/__init__.py
probablyprofit/config.py
probablyprofit/main.py
probablyprofit/py.typed
probablyprofit/agent/__init__.py
probablyprofit/agent/anthropic_agent.py
probablyprofit/agent/base.py
probablyprofit/agent/ensemble.py
probablyprofit/agent/fallback.py
probablyprofit/agent/formatters.py
probablyprofit/agent/gemini_agent.py
probablyprofit/agent/intelligence.py
probablyprofit/agent/mock_agent.py
probablyprofit/agent/openai_agent.py
probablyprofit/agent/strategy.py
probablyprofit/agent/strategy_version.py
probablyprofit/alerts/__init__.py
probablyprofit/alerts/telegram.py
probablyprofit/api/__init__.py
probablyprofit/api/async_wrapper.py
probablyprofit/api/client.py
probablyprofit/api/exceptions.py
probablyprofit/api/order_manager.py
probablyprofit/api/platform.py
probablyprofit/api/signer.py
probablyprofit/api/websocket.py
probablyprofit/backtesting/__init__.py
probablyprofit/backtesting/data.py
probablyprofit/backtesting/engine.py
probablyprofit/backtesting/metrics.py
probablyprofit/backtesting/optimizer.py
probablyprofit/cli/__init__.py
probablyprofit/cli/main.py
probablyprofit/plugins/__init__.py
probablyprofit/plugins/base.py
probablyprofit/plugins/examples.py
probablyprofit/plugins/hooks.py
probablyprofit/plugins/registry.py
probablyprofit/plugins/community/__init__.py
probablyprofit/plugins/community/discord_plugin.py
probablyprofit/plugins/community/twitter_sentiment.py
probablyprofit/risk/__init__.py
probablyprofit/risk/manager.py
probablyprofit/risk/positions.py
probablyprofit/scripts/optimize.py
probablyprofit/scripts/setup_wizard.py
probablyprofit/scripts/verify_agents_loading.py
probablyprofit/scripts/verify_api.py
probablyprofit/scripts/verify_kelly.py
probablyprofit/scripts/verify_plugins.py
probablyprofit/sources/__init__.py
probablyprofit/sources/aggregator.py
probablyprofit/sources/perplexity.py
probablyprofit/sources/reddit.py
probablyprofit/sources/sentiment.py
probablyprofit/sources/trends.py
probablyprofit/sources/twitter.py
probablyprofit-1.2.0.dist-info/licenses/LICENSE
probablyprofit-1.2.0.dist-info/METADATA
probablyprofit-1.2.0.dist-info/WHEEL
probablyprofit-1.2.0.dist-info/entry_points.txt
probablyprofit-1.2.0.dist-info/top_level.txt
probablyprofit-1.2.0.dist-info/RECORD
