Metadata-Version: 2.4
Name: probablyprofit
Version: 1.2.0
Summary: AI-powered prediction market trading bots. Write strategy in English, let AI trade for you.
Author-email: ProbablyProfit Contributors <hello@probablyprofit.dev>
License: MIT
Project-URL: Homepage, https://github.com/randomness11/probablyprofit
Project-URL: Documentation, https://github.com/randomness11/probablyprofit#readme
Project-URL: Repository, https://github.com/randomness11/probablyprofit
Keywords: polymarket,prediction-markets,trading-bot,ai,llm,gpt,claude,automated-trading,crypto
Classifier: Development Status :: 4 - Beta
Classifier: Environment :: Console
Classifier: Intended Audience :: Developers
Classifier: Intended Audience :: Financial and Insurance Industry
Classifier: License :: OSI Approved :: MIT License
Classifier: Operating System :: OS Independent
Classifier: Programming Language :: Python :: 3
Classifier: Programming Language :: Python :: 3.10
Classifier: Programming Language :: Python :: 3.11
Classifier: Programming Language :: Python :: 3.12
Classifier: Topic :: Office/Business :: Financial :: Investment
Classifier: Topic :: Scientific/Engineering :: Artificial Intelligence
Classifier: Typing :: Typed
Requires-Python: >=3.10
License-File: LICENSE
Requires-Dist: click>=8.1.0
Requires-Dist: rich>=13.0.0
Requires-Dist: httpx>=0.27.0
Requires-Dist: aiohttp>=3.9.0
Requires-Dist: pydantic>=2.0.0
Requires-Dist: pydantic-settings>=2.0.0
Requires-Dist: pyyaml>=6.0
Requires-Dist: python-dotenv>=1.0.0
Requires-Dist: loguru>=0.7.0
Requires-Dist: tenacity>=8.2.0
Provides-Extra: openai
Requires-Dist: openai>=1.0.0; extra == "openai"
Provides-Extra: anthropic
Requires-Dist: anthropic>=0.39.0; extra == "anthropic"
Provides-Extra: google
Requires-Dist: google-genai>=1.0.0; extra == "google"
Provides-Extra: ai
Requires-Dist: openai>=1.0.0; extra == "ai"
Requires-Dist: anthropic>=0.39.0; extra == "ai"
Requires-Dist: google-genai>=1.0.0; extra == "ai"
Provides-Extra: polymarket
Requires-Dist: eth-account>=0.11.0; extra == "polymarket"
Requires-Dist: web3>=6.0.0; extra == "polymarket"
Requires-Dist: py-clob-client>=0.20.0; extra == "polymarket"
Requires-Dist: websockets>=12.0; extra == "polymarket"
Provides-Extra: intel
Requires-Dist: tweepy>=4.14.0; extra == "intel"
Requires-Dist: feedparser>=6.0.0; extra == "intel"
Requires-Dist: beautifulsoup4>=4.12.0; extra == "intel"
Provides-Extra: data
Requires-Dist: pandas>=2.0.0; extra == "data"
Requires-Dist: numpy>=1.24.0; extra == "data"
Provides-Extra: db
Requires-Dist: sqlmodel>=0.0.14; extra == "db"
Requires-Dist: alembic>=1.12.0; extra == "db"
Requires-Dist: aiosqlite>=0.19.0; extra == "db"
Requires-Dist: greenlet>=3.0.0; extra == "db"
Provides-Extra: full
Requires-Dist: probablyprofit[ai,data,db,intel,polymarket]; extra == "full"
Provides-Extra: dev
Requires-Dist: pytest>=7.4.0; extra == "dev"
Requires-Dist: pytest-asyncio>=0.21.0; extra == "dev"
Requires-Dist: pytest-cov>=4.1.0; extra == "dev"
Requires-Dist: pytest-timeout>=2.2.0; extra == "dev"
Requires-Dist: black>=23.0.0; extra == "dev"
Requires-Dist: isort>=5.12.0; extra == "dev"
Requires-Dist: ruff>=0.1.0; extra == "dev"
Requires-Dist: mypy>=1.5.0; extra == "dev"
Requires-Dist: pre-commit>=3.7.0; extra == "dev"
Requires-Dist: bandit[toml]>=1.7.0; extra == "dev"
Dynamic: license-file
